quant_framework/__init__.py
quant_framework/main.py
quant_framework/mock_broker.py
quant_framework/mock_data_provider.py
quant_framework/strategy.py
quant_framework/brokers/__init__.py
quant_framework/brokers/broker.py
quant_framework/brokers/mock_broker.py
quant_framework/data_providers/__init__.py
quant_framework/data_providers/data_provider.py
quant_framework/data_providers/eod_historical_data.py
quant_framework/data_providers/mock_data_provider.py
quant_framework/internal/__init__.py
quant_framework/internal/configuration.py
quant_framework/internal/models/__init__.py
quant_framework/internal/models/base.py
quant_framework/internal/models/data_provider.py
quant_framework/internal/models/historical_price.py
quant_framework/internal/models/strategy.py
quant_framework/internal/utils/__init__.py
quant_framework/internal/utils/backtest.py
quant_framework/internal/utils/db.py
quant_framework/internal/utils/strategy_loader.py
quant_framework/internal/www/__init__.py
quant_framework/internal/www/app.py
quant_framework/strategies/__init__.py
quant_framework/strategies/mock_buy_and_hold.py
quant_framework/strategies/strategy.py
quant_framework-0.0.5.dist-info/METADATA
quant_framework-0.0.5.dist-info/WHEEL
quant_framework-0.0.5.dist-info/entry_points.txt
quant_framework-0.0.5.dist-info/top_level.txt
quant_framework-0.0.5.dist-info/RECORD
