Metadata-Version: 2.1
Name: quant-framework
Version: 0.0.5
Summary: A basic framework for backtesting and going live with quant strategies
Home-page: https://github.com/brendangeck/quant-framework
Author: Brendan Geck
Author-email: bpgeck@gmail.com
License: UNKNOWN
Platform: UNKNOWN
Classifier: Programming Language :: Python :: 3
Classifier: License :: OSI Approved :: MIT License
Classifier: Operating System :: OS Independent
Requires-Dist: croniter (==1.0.6)
Requires-Dist: Flask (==1.1.2)
Requires-Dist: psycopg2-binary (==2.8.6)
Requires-Dist: python-dateutil (==2.8.1)
Requires-Dist: SQLAlchemy (==1.3.23)
